{
  "description": "Nonlinear Optimization Models for Julia",
  "title": "NLPModels.jl",
  "upload_type": "software",
  "publication_date": "2019-02-06",
  "creators": [
    {
      "affiliation": "Federal University of Paran\u00e1 - UFPR",
      "name": "Abel Soares Siqueira"
    },
    {
      "affiliation": "\u00c9cole Polytechnique/GERAD - Montr\u00e9al",
      "name": "Dominique Orban"
    }
  ],
  "access_right": "open",
  "related_identifiers": [
    {
      "scheme": "url",
      "identifier": "https://github.com/JuliaSmoothOptimizers/NLPModels.jl/releases/latest",
      "relation": "isSupplementTo"
    }
  ]
}
